LICENSE
MANIFEST.in
README
distribute_setup.py
setup.py
asp/__init__.py
asp/config.py
asp/tree_grammar.py
asp/util.py
asp.egg-info/PKG-INFO
asp.egg-info/SOURCES.txt
asp.egg-info/dependency_links.txt
asp.egg-info/requires.txt
asp.egg-info/top_level.txt
asp/codegen/__init__.py
asp/codegen/ast_tools.py
asp/codegen/cpp_ast.py
asp/codegen/python_ast.py
asp/codegen/templating/__init__.py
asp/codegen/templating/template.py
asp/jit/__init__.py
asp/jit/asp_module.py
asp/jit/variant_history.py
asp/ply/__init__.py
asp/ply/cpp.py
asp/ply/ctokens.py
asp/ply/lex.py
asp/ply/yacc.py
doc/Makefile
doc/codegen.rst
doc/conf.py
doc/index.rst
doc/jit.rst
doc/make.bat
doc/misc/Par Lab All presentation.pptx
doc/misc/using_eclipse_with_pydev_on_ubuntu.txt
specializers/run_tests.sh
specializers/array_doubler/array_doubler.py
specializers/array_doubler/run_tests.sh
specializers/array_doubler/templates/double_template.mako
specializers/array_doubler/tests/arraydoubler_test.py
tests/asp_module_tests.py
tests/ast_tools_test.py
tests/codegen_test.py
tests/config_test.py
tests/cpp_ast_test.py
tests/cpuinfo
tests/cuda_test.py
tests/pickled_ast
tests/platform_detector_test.py