Metadata-Version: 1.0
Name: asp
Version: 0.1.2.3
Summary: ASP is a SEJITS (specialized embedded just-in-time compiler) toolkit for Python.
Home-page: http://github.com/shoaibkamil/asp/wiki/
Author: Shoaib Kamil, Derrick Coetzee, Henry Cook, and others
Author-email: skamil@cs.berkeley.edu
License: BSD
Platform: UNKNOWN
Classifier: Development Status :: 2 - Pre-Alpha
Classifier: Intended Audience :: Developers
Classifier: Intended Audience :: Other Audience
Classifier: Intended Audience :: Science/Research
Classifier: License :: OSI Approved :: BSD License
Classifier: Natural Language :: English
Classifier: Programming Language :: Python
Classifier: Topic :: Scientific/Engineering
Classifier: Topic :: Software Development :: Libraries
Classifier: Topic :: Utilities
